flyfield/__init__.py
flyfield/cli.py
flyfield/config.py
flyfield/extract.py
flyfield/io_utils.py
flyfield/layout.py
flyfield/main.py
flyfield/markup_and_fields.py
flyfield/utils.py
flyfield-2025.9.17.dist-info/licenses/LICENSE
tests/__init__.py
tests/test_extract.py
tests/test_io_utils.py
tests/test_layout.py
tests/test_main.py
tests/test_markup_and_fields.py
tests/test_utils.py
flyfield-2025.9.17.dist-info/METADATA
flyfield-2025.9.17.dist-info/WHEEL
flyfield-2025.9.17.dist-info/entry_points.txt
flyfield-2025.9.17.dist-info/top_level.txt
flyfield-2025.9.17.dist-info/RECORD
