Metadata-Version: 2.4
Name: flyfield
Version: 2025.9.17
Summary: Tools for extracting, processing, and generating interactive fields for PDFs containing white box fields.
Author-email: flywire <flywire0@gmail.com>
License: GPL-3.0-or-later
Keywords: pdf,form,fields,extraction,pymupdf,pypdfforms
Classifier: Development Status :: 5 - Production/Stable
Classifier: Intended Audience :: Developers
Classifier: License :: OSI Approved :: GNU General Public License v3 or later (GPLv3+)
Classifier: Programming Language :: Python :: 3
Classifier: Programming Language :: Python :: 3.9
Classifier: Programming Language :: Python :: 3.11
Classifier: Programming Language :: Python :: 3.12
Classifier: Programming Language :: Python :: 3.13
Classifier: Topic :: Software Development :: Libraries
Requires-Python: >=3.9
License-File: LICENSE
Requires-Dist: PyMuPDF>=1.18.0
Requires-Dist: PyPDFForm>=0.3.3
Provides-Extra: dev
Requires-Dist: mkdocs>=1.4; extra == "dev"
Requires-Dist: mkdocs-material>=9.1; extra == "dev"
Requires-Dist: mkdocstrings[python]>=0.19; extra == "dev"
Requires-Dist: black>=23.3.0; extra == "dev"
Requires-Dist: isort>=5.12.0; extra == "dev"
Requires-Dist: pytest>=7.4; extra == "dev"
Requires-Dist: tox>=4.19; extra == "dev"
Dynamic: license-file
